jaxkit/__init__.py
jaxkit/fully_connected.py
jaxkit/utils.py
jaxkit-0.0.2.dist-info/LICENSE
jaxkit-0.0.2.dist-info/METADATA
jaxkit-0.0.2.dist-info/WHEEL
jaxkit-0.0.2.dist-info/top_level.txt
jaxkit-0.0.2.dist-info/RECORD
